{"head":{"manifestVersion":"1.0.0"},"body":"{\"version\":\"0.0.18\",\"contract\":{\"hash\":\"21XWnNJLturqK9qjx1yQ6VXCihSwrn2bd7Jre5hEDNfNwg9MaJ\",\"file\":\"chatroom.js\"},\"authors\":[{\"cipher\":\"algo\",\"key\":\"<pubkey from deploy-key.json>\"},{\"cipher\":\"algo\",\"key\":\"<pubkey from alex.json>\"}],\"contractSlim\":{\"file\":\"chatroom-slim.js\",\"hash\":\"21XWnNNmjUcnJ1yxJ9jcuYtKcbxTXbw3XnQRr6eyzCa6FXEaEX\"}}","signature":{"key":"<which of the 'authors' keys was used to sign 'body'>","signature":"<signature>"}}