{"head":{"manifestVersion":"1.0.0"},"body":"{\"version\":\"0.0.23\",\"contract\":{\"hash\":\"21XWnNQvv4uKQ81K3STAhrBnnJgP9u8kUGt9Dp1cWidiY3GKoJ\",\"file\":\"group.js\"},\"authors\":[{\"cipher\":\"algo\",\"key\":\"<pubkey from deploy-key.json>\"},{\"cipher\":\"algo\",\"key\":\"<pubkey from alex.json>\"}],\"contractSlim\":{\"file\":\"group-slim.js\",\"hash\":\"21XWnNTFuESvmzPR6jjfwDa4jKbr57Wes7YPhM4fGmfuENjam3\"}}","signature":{"key":"<which of the 'authors' keys was used to sign 'body'>","signature":"<signature>"}}